vrt_lss_monitor/__init__.py
vrt_lss_monitor/api_client.py
vrt_lss_monitor/api_response.py
vrt_lss_monitor/configuration.py
vrt_lss_monitor/exceptions.py
vrt_lss_monitor/py.typed
vrt_lss_monitor/rest.py
vrt_lss_monitor/api/__init__.py
vrt_lss_monitor/api/backups_api.py
vrt_lss_monitor/api/crews_api.py
vrt_lss_monitor/api/custom_fields_api.py
vrt_lss_monitor/api/custom_icons_api.py
vrt_lss_monitor/api/deals_api.py
vrt_lss_monitor/api/explorer_api.py
vrt_lss_monitor/api/facts_api.py
vrt_lss_monitor/api/hardlinks_api.py
vrt_lss_monitor/api/locations_api.py
vrt_lss_monitor/api/orders_api.py
vrt_lss_monitor/api/performers_api.py
vrt_lss_monitor/api/system_api.py
vrt_lss_monitor/api/transports_api.py
vrt_lss_monitor/api/trips_api.py
vrt_lss_monitor/api/user_api.py
vrt_lss_monitor/api/waves_api.py
vrt_lss_monitor/models/__init__.py
vrt_lss_monitor/models/actualize_settings.py
vrt_lss_monitor/models/assigned_performer.py
vrt_lss_monitor/models/assigned_transport.py
vrt_lss_monitor/models/attribute.py
vrt_lss_monitor/models/basic_state.py
vrt_lss_monitor/models/box.py
vrt_lss_monitor/models/box_compatibilities.py
vrt_lss_monitor/models/box_limits.py
vrt_lss_monitor/models/break_rules.py
vrt_lss_monitor/models/calculation_info.py
vrt_lss_monitor/models/calculation_settings.py
vrt_lss_monitor/models/calculation_state.py
vrt_lss_monitor/models/calculation_status.py
vrt_lss_monitor/models/capacity.py
vrt_lss_monitor/models/capacity_cost.py
vrt_lss_monitor/models/capacity_limit.py
vrt_lss_monitor/models/capacity_multiplier.py
vrt_lss_monitor/models/capacity_statistics_load.py
vrt_lss_monitor/models/capacity_statistics_ratio.py
vrt_lss_monitor/models/capacity_statistics_sum.py
vrt_lss_monitor/models/cargo.py
vrt_lss_monitor/models/cargo_action.py
vrt_lss_monitor/models/cargo_action_type.py
vrt_lss_monitor/models/cargo_compatibilities.py
vrt_lss_monitor/models/cargo_rotation_type.py
vrt_lss_monitor/models/check_result.py
vrt_lss_monitor/models/compatibility_penalty.py
vrt_lss_monitor-7.29.3120.dist-info/METADATA
vrt_lss_monitor-7.29.3120.dist-info/WHEEL
vrt_lss_monitor-7.29.3120.dist-info/top_level.txt
vrt_lss_monitor-7.29.3120.dist-info/RECORD
